jaxcam/__init__.py
jaxcam/io.py
jaxcam/_src/camera.py
jaxcam/_src/io.py
jaxcam/_src/math.py
jaxcam/_src/rays.py
jaxcam/_src/utils.py
jaxcam-0.3.0.dist-info/LICENSE
jaxcam-0.3.0.dist-info/WHEEL
jaxcam-0.3.0.dist-info/METADATA
jaxcam-0.3.0.dist-info/RECORD
