Metadata-Version: 2.1
Name: jaxcam
Version: 0.3.0
Summary: 
Keywords: 
Author-email: jaxcam authors <jaxcam@google.com>
Requires-Python: >=3.8
Classifier: License :: OSI Approved :: Apache Software License
Classifier: Intended Audience :: Science/Research
Requires-Dist: jax
Requires-Dist: flax
Requires-Dist: numpy
Requires-Dist: etils[epath]
Requires-Dist: pytest ; extra == "dev"
Requires-Dist: pytest-xdist ; extra == "dev"
Requires-Dist: pylint>=2.6.0 ; extra == "dev"
Requires-Dist: pyink ; extra == "dev"
Requires-Dist: absl-py ; extra == "dev"
Project-URL: changelog, https://github.com/google/jaxcam/blob/main/CHANGELOG.md
Project-URL: homepage, https://github.com/google/jaxcam
Project-URL: repository, https://github.com/google/jaxcam
Provides-Extra: dev
